LICENSE
MANIFEST.in
README.md
requirements.txt
setup.cfg
setup.py
categories/__init__.py
categories/admin.py
categories/constants.py
categories/models.py
categories/translation.py
categories/locale/ru/LC_MESSAGES/django.mo
categories/locale/ru/LC_MESSAGES/django.po
categories/locale/uk/LC_MESSAGES/django.mo
categories/locale/uk/LC_MESSAGES/django.po
categories/migrations/0001_initial.py
categories/migrations/__init__.py
categories/templatetags/__init__.py
categories/templatetags/categories.py
django_mp_clothes_categories.egg-info/PKG-INFO
django_mp_clothes_categories.egg-info/SOURCES.txt
django_mp_clothes_categories.egg-info/dependency_links.txt
django_mp_clothes_categories.egg-info/requires.txt
django_mp_clothes_categories.egg-info/top_level.txt