Metadata-Version: 1.1
Name: django-mp-clothes-categories
Version: 0.2
Summary: Django clothes categories app
Home-page: https://github.com/pmaigutyak/mp-clothes-categories
Author: Paul Maigutyak
Author-email: pmaigutyak@gmail.com
License: MIT
Download-URL: https://github.com/pmaigutyak/mp-clothes-categories/archive/0.2.tar.gz
Platform: UNKNOWN
